{
  "$schema": "https://schema.management.azure.com/schemas/2015-01-01/deploymentTemplate.json#",
  "contentVersion": "1.0.0.0",
  "parameters": {
    "virtualMachineName": {
      "type": "string",
      "defaultValue": "HashcatVM",
      "minLength": 1
    },
    "vmSize": {
      "type": "string",
      "defaultValue": "Standard_NV6_Promo",
      "metadata": {
        "description": "VM size for the hashcat server. (see https://azureprice.net/)"
      },
      "allowedValues": [
        "Standard_NV6_Promo",
        "Standard_NV6",
        "Standard_NV12_Promo",
        "Standard_NV12",
        "Standard_NV24_Promo",
        "Standard_NV24",
        "Standard_NV6s_v2",
        "Standard_NV12s_v2"
      ]
    },
    "adminUsername": {
      "type": "string",
      "minLength": 1
    },
    "adminPublicKey": {
      "type": "string",
      "minLength": 1
    }
  },
  "variables": {
    "nicName": "HashcatNetworkInterface",
    "addressPrefix": "10.0.0.0/16",
    "subnetName": "Subnet",
    "subnetPrefix": "10.0.0.0/24",
    "publicIPAddressName": "HashcatPublicIP",
    "publicIPAddressType": "Dynamic",
    "vmAccountStorageName": "[concat(uniqueString( resourceGroup().id, deployment().name ), 'storage')]",
    "vmName": "HashcatVM",
    "virtualNetworkName": "HashcatNetwork",
    "vnetID": "[resourceId('Microsoft.Network/virtualNetworks',variables('virtualNetworkName'))]",
    "subnetRef": "[concat(variables('vnetID'),'/subnets/',variables('subnetName'))]"
  },
  "resources": [
    {
      "apiVersion": "2017-06-01",
      "type": "Microsoft.Network/publicIPAddresses",
      "name": "[variables('publicIPAddressName')]",
      "location": "[resourceGroup().location]",
      "properties": {
        "publicIPAllocationMethod": "[variables('publicIPAddressType')]"
      }
    },
    {
      "apiVersion": "2017-06-01",
      "type": "Microsoft.Network/virtualNetworks",
      "name": "[variables('virtualNetworkName')]",
      "location": "[resourceGroup().location]",
      "properties": {
        "addressSpace": {
          "addressPrefixes": ["[variables('addressPrefix')]"]
        },
        "subnets": [
          {
            "name": "[variables('subnetName')]",
            "properties": {
              "addressPrefix": "[variables('subnetPrefix')]"
            }
          }
        ]
      }
    },
    {
      "apiVersion": "2018-10-01",
      "type": "Microsoft.Network/networkInterfaces",
      "name": "[variables('nicName')]",
      "location": "[resourceGroup().location]",
      "dependsOn": [
        "[concat('Microsoft.Network/publicIPAddresses/', variables('publicIPAddressName'))]",
        "[concat('Microsoft.Network/virtualNetworks/', variables('virtualNetworkName'))]"
      ],
      "properties": {
        "ipConfigurations": [
          {
            "name": "ipconfig1",
            "properties": {
              "privateIPAllocationMethod": "Dynamic",
              "publicIPAddress": {
                "id": "[resourceId('Microsoft.Network/publicIPAddresses',variables('publicIPAddressName'))]"
              },
              "subnet": {
                "id": "[variables('subnetRef')]"
              }
            }
          }
        ],
        "networkSecurityGroup": {
          "id": "[resourceId('Microsoft.Network/networkSecurityGroups', 'HashcatNSG')]"
        }
      }
    },
    {
      "apiVersion": "2017-03-01",
      "type": "Microsoft.Network/networkSecurityGroups",
      "name": "HashcatNSG",
      "location": "[resourceGroup().location]",
      "tags": {
        "displayName": "NSG - Front End"
      },
      "properties": {
        "securityRules": [
          {
            "name": "SSH",
            "properties": {
              "description": "Allow inbound SSH access",
              "protocol": "Tcp",
              "sourcePortRange": "*",
              "destinationPortRange": "22",
              "sourceAddressPrefix": "Internet",
              "destinationAddressPrefix": "*",
              "access": "Allow",
              "priority": 101,
              "direction": "Inbound"
            }
          }
        ]
      }
    },
    {
      "apiVersion": "2018-06-01",
      "type": "Microsoft.Compute/virtualMachines",
      "name": "[variables('vmName')]",
      "location": "[resourceGroup().location]",
      "dependsOn": [
        "[concat('Microsoft.Network/networkInterfaces/', variables('nicName'))]"
      ],
      "properties": {
        "hardwareProfile": {
          "vmSize": "[parameters('vmSize')]"
        },
        "osProfile": {
          "computerName": "[parameters('virtualMachineName')]",
          "adminUsername": "[parameters('adminUsername')]",
          "linuxConfiguration": {
            "disablePasswordAuthentication": true,
            "ssh": {
              "publicKeys": [
                {
                  "path": "[concat('/home/', parameters('adminUsername'), '/.ssh/authorized_keys')]",
                  "keyData": "[parameters('adminPublicKey')]"
                }
              ]
            }
          }
        },
        "storageProfile": {
          "imageReference": {
            "publisher": "Canonical",
            "offer": "UbuntuServer",
            "sku": "18.04-LTS",
            "version": "latest"
          },
          "osDisk": {
            "name": "HashcatOS",
            "createOption": "FromImage",
            "managedDisk": {
              "storageAccountType": "StandardSSD_LRS"
            }
          }
        },
        "networkProfile": {
          "networkInterfaces": [
            {
              "id": "[resourceId('Microsoft.Network/networkInterfaces',variables('nicName'))]"
            }
          ]
        }
      }
    },
    {
      "type": "Microsoft.Compute/virtualMachines/extensions",
      "name": "[concat(variables('vmName'),'/CSExtension')]",
      "apiVersion": "2017-03-30",
      "location": "[resourceGroup().location]",
      "dependsOn": [
        "[concat('Microsoft.Compute/virtualMachines/', variables('vmName'))]"
      ],
      "properties": {
        "publisher": "Microsoft.Azure.Extensions",
        "type": "CustomScript",
        "typeHandlerVersion": "2.0",
        "autoUpgradeMinorVersion": true,
        "settings": {
          "fileUris": [
            "https://raw.githubusercontent.com/carlmon/Hashcat-Azure/master/azure-entrypoint.sh"
          ],
          "commandToExecute": "./azure-entrypoint.sh"
        }
      }
    }
  ],
  "outputs": {
    "adminUsername": {
      "type": "string",
      "value": "[parameters('adminUsername')]"
    }
  }
}
